<?xml version="1.0" encoding="UTF-8"?>
<Pop_geo name="allpops_auto_maf0.005geno0.1"   version="1" varfile="allpops_auto_maf0.005geno0.1.vcf.gz" indiv_label="allpops_auto_maf0.005geno0.1.indiv_label.xml" precision="0.5 degrees">
  <Population>
    <PopLabel>BantuN</PopLabel>
    <Latitude>-3</Latitude>
    <Longitude>37</Longitude>
  </Population>
  <Population>
    <PopLabel>BantuS</PopLabel>
    <Latitude>-24</Latitude>
    <Longitude>24</Longitude>
  </Population>
  <Population>
    <PopLabel>BiakaPygmies</PopLabel>
    <Latitude>4</Latitude>
    <Longitude>17</Longitude>
  </Population>
  <Population>
    <PopLabel>Mandenka</PopLabel>
    <Latitude>12</Latitude>
    <Longitude>348</Longitude>
  </Population>
  <Population>
    <PopLabel>MbutiPygmies</PopLabel>
    <Latitude>1</Latitude>
    <Longitude>29</Longitude>
  </Population>
  <Population>
    <PopLabel>San</PopLabel>
    <Latitude>-21</Latitude>
    <Longitude>20</Longitude>
  </Population>
  <Population>
    <PopLabel>Yoruba</PopLabel>
    <Latitude>8</Latitude>
    <Longitude>5</Longitude>
  </Population>
  <Population>
    <PopLabel>Adygei</PopLabel>
    <Latitude>44</Latitude>
    <Longitude>39</Longitude>
  </Population>
  <Population>
    <PopLabel>Basque</PopLabel>
    <Latitude>43</Latitude>
    <Longitude>0</Longitude>
  </Population>
  <Population>
    <PopLabel>Bergamo</PopLabel>
    <Latitude>46</Latitude>
    <Longitude>10</Longitude>
  </Population>
  <Population>
    <PopLabel>French</PopLabel>
    <Latitude>46</Latitude>
    <Longitude>2</Longitude>
  </Population>
  <Population>
    <PopLabel>Orcadian</PopLabel>
    <Latitude>59</Latitude>
    <Longitude>357</Longitude>
  </Population>
  <Population>
    <PopLabel>Russian</PopLabel>
    <Latitude>61</Latitude>
    <Longitude>40</Longitude>
  </Population>
  <Population>
    <PopLabel>Sardinian</PopLabel>
    <Latitude>40</Latitude>
    <Longitude>9</Longitude>
  </Population>
  <Population>
    <PopLabel>Tuscan</PopLabel>
    <Latitude>43</Latitude>
    <Longitude>11</Longitude>
  </Population>
  <Population>
    <PopLabel>Bedouin</PopLabel>
    <Latitude>31</Latitude>
    <Longitude>35</Longitude>
  </Population>
  <Population>
    <PopLabel>Druze</PopLabel>
    <Latitude>32</Latitude>
    <Longitude>35</Longitude>
  </Population>
  <Population>
    <PopLabel>Mozabite</PopLabel>
    <Latitude>32</Latitude>
    <Longitude>3</Longitude>
  </Population>
  <Population>
    <PopLabel>Palestinian</PopLabel>
    <Latitude>32</Latitude>
    <Longitude>35</Longitude>
  </Population>
  <Population>
    <PopLabel>Balochi</PopLabel>
    <Latitude>30.5</Latitude>
    <Longitude>66.5</Longitude>
  </Population>
  <Population>
    <PopLabel>Brahui</PopLabel>
    <Latitude>30.5</Latitude>
    <Longitude>66.5</Longitude>
  </Population>
  <Population>
    <PopLabel>Burusho</PopLabel>
    <Latitude>36.5</Latitude>
    <Longitude>74</Longitude>
  </Population>
  <Population>
    <PopLabel>Hazara</PopLabel>
    <Latitude>33.5</Latitude>
    <Longitude>70</Longitude>
  </Population>
  <Population>
    <PopLabel>Kalash</PopLabel>
    <Latitude>36</Latitude>
    <Longitude>71.5</Longitude>
  </Population>
  <Population>
    <PopLabel>Makrani</PopLabel>
    <Latitude>26</Latitude>
    <Longitude>64</Longitude>
  </Population>
  <Population>
    <PopLabel>Pathan</PopLabel>
    <Latitude>33.5</Latitude>
    <Longitude>70.5</Longitude>
  </Population>
  <Population>
    <PopLabel>Sindhi</PopLabel>
    <Latitude>25.5</Latitude>
    <Longitude>69</Longitude>
  </Population>
  <Population>
    <PopLabel>Uygur</PopLabel>
    <Latitude>44</Latitude>
    <Longitude>81</Longitude>
  </Population>
  <Population>
    <PopLabel>Xibo</PopLabel>
    <Latitude>43.5</Latitude>
    <Longitude>81.5</Longitude>
  </Population>
  <Population>
    <PopLabel>Cambodian</PopLabel>
    <Latitude>12</Latitude>
    <Longitude>105</Longitude>
  </Population>
  <Population>
    <PopLabel>Dai</PopLabel>
    <Latitude>21</Latitude>
    <Longitude>100</Longitude>
  </Population>
  <Population>
    <PopLabel>Daur</PopLabel>
    <Latitude>48.5</Latitude>
    <Longitude>124</Longitude>
  </Population>
  <Population>
    <PopLabel>Han</PopLabel>
    <Latitude>32.5</Latitude>
    <Longitude>114</Longitude>
  </Population>
  <Population>
    <PopLabel>Hezhen</PopLabel>
    <Latitude>47.5</Latitude>
    <Longitude>133.5</Longitude>
  </Population>
  <Population>
    <PopLabel>Japanese</PopLabel>
    <Latitude>38</Latitude>
    <Longitude>138</Longitude>
  </Population>
  <Population>
    <PopLabel>Lahu</PopLabel>
    <Latitude>22</Latitude>
    <Longitude>100</Longitude>
  </Population>
  <Population>
    <PopLabel>Miaozu</PopLabel>
    <Latitude>28</Latitude>
    <Longitude>109</Longitude>
  </Population>
  <Population>
    <PopLabel>Mongola</PopLabel>
    <Latitude>48.5</Latitude>
    <Longitude>119</Longitude>
  </Population>
  <Population>
    <PopLabel>Naxi</PopLabel>
    <Latitude>26</Latitude>
    <Longitude>100</Longitude>
  </Population>
  <Population>
    <PopLabel>Oroqen</PopLabel>
    <Latitude>50.5</Latitude>
    <Longitude>126.5</Longitude>
  </Population>
  <Population>
    <PopLabel>She</PopLabel>
    <Latitude>27</Latitude>
    <Longitude>119</Longitude>
  </Population>
  <Population>
    <PopLabel>Tu</PopLabel>
    <Latitude>36</Latitude>
    <Longitude>101</Longitude>
  </Population>
  <Population>
    <PopLabel>Tujia</PopLabel>
    <Latitude>29</Latitude>
    <Longitude>109</Longitude>
  </Population>
  <Population>
    <PopLabel>Yakut</PopLabel>
    <Latitude>63</Latitude>
    <Longitude>129.5</Longitude>
  </Population>
  <Population>
    <PopLabel>Yizu</PopLabel>
    <Latitude>28</Latitude>
    <Longitude>103</Longitude>
  </Population>
  <Population>
    <PopLabel>Colombian</PopLabel>
    <AltPopLabel>Piapoco/Curipaco</AltPopLabel>
    <Latitude>2</Latitude>
    <Longitude>292</Longitude>
  </Population>
  <Population>
    <PopLabel>Karitiana</PopLabel>
    <Latitude>-10</Latitude>
    <Longitude>297</Longitude>
  </Population>
  <Population>
    <PopLabel>Maya</PopLabel>
    <Latitude>19</Latitude>
    <Longitude>269</Longitude>
  </Population>
  <Population>
    <PopLabel>Pima</PopLabel>
    <Latitude>29</Latitude>
    <Longitude>252</Longitude>
  </Population>
  <Population>
    <PopLabel>Surui</PopLabel>
    <Latitude>-11</Latitude>
    <Longitude>298</Longitude>
  </Population>
  <Population>
    <PopLabel>Melanesian</PopLabel>
    <Latitude>-6</Latitude>
    <Longitude>155</Longitude>
  </Population>
  <Population>
    <PopLabel>Papuan</PopLabel>
    <Latitude>-4</Latitude>
    <Longitude>143</Longitude>
  </Population>
  <Population>
    <PopLabel>Europe</PopLabel>
    <Latitude>50</Latitude>
    <Longitude>26</Longitude>
  </Population>
  <Population>
    <PopLabel>Africa</PopLabel>
    <Latitude>8</Latitude>
    <Longitude>24</Longitude>
  </Population>
  <Population>
    <PopLabel>E_Asia</PopLabel>
    <Latitude>35</Latitude>
    <Longitude>97</Longitude>
  </Population>
  <Population>
    <PopLabel>America</PopLabel>
    <Latitude>15</Latitude>
    <Longitude>270</Longitude>
  </Population>
  <Population>
    <PopLabel>Central_Asia</PopLabel>
    <Latitude>33</Latitude>
    <Longitude>57</Longitude>
  </Population>
  <Population>
    <PopLabel>Europe</PopLabel>
    <Latitude>50</Latitude>
    <Longitude>26</Longitude>
  </Population>
  <Population>
    <PopLabel>Near_East/N_Africa</PopLabel>
    <Latitude>28</Latitude>
    <Longitude>25</Longitude>
  </Population>
  <Population>
    <PopLabel>Oceania</PopLabel>
    <Latitude>9</Latitude>
    <Longitude>129</Longitude>
  </Population>
</Pop_geo>
